live_calc/__init__.py
live_calc/__main__.py
live_calc/calc_parser.py
live_calc/web/app.html
live_calc/web/script.js
live_calc/web/style.css
live_calc-0.0.2.dist-info/METADATA
live_calc-0.0.2.dist-info/WHEEL
live_calc-0.0.2.dist-info/licenses/LICENSE
live_calc-0.0.2.dist-info/RECORD
