Metadata-Version: 2.4
Name: live_calc
Version: 0.0.2
Summary: A live python calculator
Author-email: Thomas Godden <thomas.godden@outlook.com>
License-File: LICENSE
Classifier: License :: OSI Approved :: MIT License
Classifier: Operating System :: OS Independent
Classifier: Programming Language :: Python :: 3
Requires-Python: >=3.8
Requires-Dist: eel
Requires-Dist: numpy
Requires-Dist: pint
